uvinstaller/__init__.py
uvinstaller/cli.py
uvinstaller/dependency_analyzer.py
uvinstaller/packager.py
uvinstaller/uv_installer.py
uvinstaller-1.0.0.dist-info/METADATA
uvinstaller-1.0.0.dist-info/WHEEL
uvinstaller-1.0.0.dist-info/entry_points.txt
uvinstaller-1.0.0.dist-info/licenses/LICENSE
uvinstaller-1.0.0.dist-info/RECORD
