Metadata-Version: 2.4
Name: uvinstaller
Version: 1.0.0
Summary: 使用uv和pyinstaller自动打包Python应用的工具
Project-URL: Homepage, https://github.com/uvinstaller/uvinstaller
Project-URL: Repository, https://github.com/uvinstaller/uvinstaller
Project-URL: Issues, https://github.com/uvinstaller/uvinstaller/issues
Author-email: uvinstaller <uvinstaller@example.com>
License: MIT
License-File: LICENSE
Keywords: packaging,pyinstaller,python,uv
Classifier: Development Status :: 4 - Beta
Classifier: Intended Audience :: Developers
Classifier: License :: OSI Approved :: MIT License
Classifier: Operating System :: OS Independent
Classifier: Programming Language :: Python :: 3
Classifier: Programming Language :: Python :: 3.8
Classifier: Programming Language :: Python :: 3.9
Classifier: Programming Language :: Python :: 3.10
Classifier: Programming Language :: Python :: 3.11
Classifier: Programming Language :: Python :: 3.12
Classifier: Topic :: Software Development :: Build Tools
Classifier: Topic :: System :: Archiving :: Packaging
Requires-Python: >=3.8
Requires-Dist: packaging>=21.0
Requires-Dist: requests>=2.25.0
Provides-Extra: dev
Requires-Dist: black>=21.0; extra == 'dev'
Requires-Dist: flake8>=3.8; extra == 'dev'
Requires-Dist: isort>=5.0; extra == 'dev'
Requires-Dist: pytest>=6.0; extra == 'dev'
